qtoggleserver/mppsolar/__init__.py
qtoggleserver/mppsolar/bluetooth.py
qtoggleserver/mppsolar/constants.py
qtoggleserver/mppsolar/exceptions.py
qtoggleserver/mppsolar/inverter.py
qtoggleserver/mppsolar/io.py
qtoggleserver/mppsolar/ports.py
qtoggleserver/mppsolar/serial.py
qtoggleserver/mppsolar/typing.py
qtoggleserver/mppsolar/commands/__init__.py
qtoggleserver/mppsolar/commands/base.py
qtoggleserver/mppsolar/commands/mchgc.py
qtoggleserver/mppsolar/commands/mnchgc.py
qtoggleserver/mppsolar/commands/muchgc.py
qtoggleserver/mppsolar/commands/pbatmaxdisc.py
qtoggleserver/mppsolar/commands/pbcv.py
qtoggleserver/mppsolar/commands/pbdv.py
qtoggleserver/mppsolar/commands/pbft.py
qtoggleserver/mppsolar/commands/pbt.py
qtoggleserver/mppsolar/commands/pcp.py
qtoggleserver/mppsolar/commands/pcvv.py
qtoggleserver/mppsolar/commands/pop.py
qtoggleserver/mppsolar/commands/psdv.py
qtoggleserver/mppsolar/commands/qmchgcr.py
qtoggleserver/mppsolar/commands/qmod.py
qtoggleserver/mppsolar/commands/qmuchgcr.py
qtoggleserver/mppsolar/commands/qpigs.py
qtoggleserver/mppsolar/commands/qpigs2.py
qtoggleserver/mppsolar/commands/qpiri.py
qtoggleserver_mppsolar-1.7.0.dist-info/licenses/LICENSE.txt
qtoggleserver_mppsolar-1.7.0.dist-info/METADATA
qtoggleserver_mppsolar-1.7.0.dist-info/WHEEL
qtoggleserver_mppsolar-1.7.0.dist-info/top_level.txt
qtoggleserver_mppsolar-1.7.0.dist-info/RECORD
