Metadata-Version: 2.4
Name: qtoggleserver-mppsolar
Version: 1.7.0
Summary: MPP Solar inverters support for qToggleServer
Author-email: Calin Crisan <ccrisan@gmail.com>
License: Apache 2.0
Requires-Python: >=3.11
License-File: LICENSE.txt
Requires-Dist: pyserial
Dynamic: license-file
